{
  "project_info": {
    "project_number": "518415173935",
    "project_id": "multiflex-team",
    "storage_bucket": "multiflex-team.appspot.com"
  },
  "client": [
    {
      "client_info": {
        "mobilesdk_app_id": "1:518415173935:android:8df2a8abd1538fe9fb39da",
        "android_client_info": {
          "package_name": "com.multiflex"
        }
      },
      "oauth_client": [
        {
          "client_id": "518415173935-i55rmtqjbsmosksduv4f53nftsbc8vqo.apps.googleusercontent.com",
          "client_type": 1,
          "android_info": {
            "package_name": "com.multiflex",
            "certificate_hash": "97503d11adf517528e2ea3cb7c2cf38201850fde"
          }
        },
        {
          "client_id": "518415173935-c1vacu8gtnbbjotglgvregpunl1mthnm.apps.googleusercontent.com",
          "client_type": 3
        }
      ],
      "api_key": [
        {
          "current_key": "AIzaSyB6SqbP4f5oMDu49CPLeVWsm8Ix9vY5jgU"
        }
      ],
      "services": {
        "appinvite_service": {
          "other_platform_oauth_client": [
            {
              "client_id": "518415173935-c1vacu8gtnbbjotglgvregpunl1mthnm.apps.googleusercontent.com",
              "client_type": 3
            }
          ]
        }
      }
    }
  ],
  "configuration_version": "1"
}